pipeline_optuna/__init__.py
pipeline_optuna/evaluate.py
pipeline_optuna/regression_model.py
pipeline_optuna/system_optimize.py
pipeline_optuna-0.0.7.dist-info/LICENSE
pipeline_optuna-0.0.7.dist-info/METADATA
pipeline_optuna-0.0.7.dist-info/WHEEL
pipeline_optuna-0.0.7.dist-info/top_level.txt
pipeline_optuna-0.0.7.dist-info/RECORD
